{"classes": ["SUBSCRIPTION_TYPE","SUBSCRIPTION_EXPENSE", "FOOD_EXPENSE", "FOOD_ITEM", "TRAVEL_MODE", "TRAVEL_EXPENSE", "TRAVEL_DESTINATION", "CLOTHING_EXPENSE", "CLOTHING_TYPE"],
    "annotations": [
      ["Renewed my Netflix subscription for Rs 2000 this month\r", {"entities": [[11,18,"SUBSCRIPTION_TYPE"]]}],
      ["Renewed my Amazon Prime membership for Rs 1500 this year\r",{"entities": [[11,23,"SUBSCRIPTION_TYPE"], [42,46,"SUBSCRIPTION_EXPENSE"]]}],
      ["Subscribed to HBO Max for Rs 500 per month\r",{"entities": [[14,21,"SUBSCRIPTION_TYPE"],[29,32,"SUBSCRIPTION_EXPENSE"]]}],      
      ["Renewed my Spotify Premium subscription for Rs 250 this month\r",{"entities": [[11,26,"SUBSCRIPTION_TYPE"],[47,50,"SUBSCRIPTION_EXPENSE"]]}],      
      ["Subscribed to Apple Music for Rs 200 per month\r",{"entities": [[14,25,"SUBSCRIPTION_TYPE"],[33,36,"SUBSCRIPTION_EXPENSE"]]}],
      ["Renewed my Disney Plus subscription for Rs 300 this month\r",{"entities": [[11,12,"SUBSCRIPTION_TYPE" ],[43,46,"SUBSCRIPTION_EXPENSE"]]}],
      ["Subscribed to YouTube Premium for Rs 400 per month\r",{ "entities": [[14,29,"SUBSCRIPTION_TYPE"],[37,40,"SUBSCRIPTION_EXPENSE"]]}],
      ["Renewed my Audible membership for Rs 1000 this year\r", {"entities": [[11,18,"SUBSCRIPTION_TYPE"],[37,41,"SUBSCRIPTION_EXPENSE"]]}],

      ["I spent Rs 110 on chicken burger today\r",{"entities":[[11,14,"FOOD_EXPENSE"],[18,32,"FOOD_ITEM"]]}],
      ["Today's snack was Rs 10 for banana.\r",{"entities":[[21,23,"FOOD_EXPENSE"],[28,34,"FOOD_ITEM"]]}],
      ["Dinner cost me Rs 300 for a delicious pizza.\r",{"entities":[[18,21,"FOOD_EXPENSE"],[28,43,"FOOD_ITEM"]]}],
      ["Chicken Biryani set me back Rs 200.\r",{"entities":[[0,15,"FOOD_ITEM"],[28,34,"FOOD_EXPENSE"]]}],
      ["I indulged in Rs 100 worth of chicken biryani.\r",{"entities":[[17,20,"FOOD_EXPENSE"],[30,45,"FOOD_ITEM"]]}],
      ["Burger and fries totaled Rs 150 for lunch.\r",{"entities":[[0,6,"FOOD_ITEM"],[11,16,"FOOD_ITEM"],[28,31,"FOOD_EXPENSE"]]}],
      ["Ice cream in the evening cost Rs 50.\r",{"entities":[[0,9,"FOOD_ITEM"],[33,35,"FOOD_EXPENSE"]]}],
      ["Sushi dinner expense was Rs 250.\r",{"entities":[[0,5,"FOOD_ITEM"],[28,31,"FOOD_EXPENSE"]]}],
      ["Grabbed a quick sandwich for Rs 80 during break.\r",{"entities":[[10,24,"FOOD_ITEM"],[32,34,"FOOD_EXPENSE"]]}],
      ["Coffee from the cafe cost Rs 30.\r",{"entities":[[0,6,"FOOD_ITEM"],[29,31,"FOOD_EXPENSE"]]}],
      ["Rs 110 chicken burger\r",{"entities":[[3,6,"FOOD_EXPENSE"],[7,21,"FOOD_ITEM"]]}],
      ["Rs 10 banana\r",{"entities":[[3,5,"FOOD_EXPENSE"],[6,12,"FOOD_ITEM"]]}],
      ["Rs 300 pizza\r",{"entities":[[3,6,"FOOD_EXPENSE"],[7,12,"FOOD_ITEM"]]}],
      ["Rs 200 Chicken Biryani\r",{"entities":[[3,6,"FOOD_EXPENSE"],[7,22,"FOOD_ITEM"]]}],
      ["Rs 100 chicken biryani\r",{"entities":[[3,6,"FOOD_EXPENSE"],[7,22,"FOOD_ITEM"]]}],
      ["Rs 150 Burger and fries\r",{"entities":[[3,6,"FOOD_EXPENSE"],[7,13,"FOOD_ITEM"],[18,23,"FOOD_ITEM"]]}],
      ["Rs 50 Ice cream\r",{"entities":[[3,5,"FOOD_EXPENSE"],[6,15,"FOOD_ITEM"]]}],
      ["Rs 250 Sushi\r",{"entities":[[3,6,"FOOD_EXPENSE"],[7,12,"FOOD_ITEM"]]}],
      ["Rs 80 sandwich\r",{"entities":[[3,5,"FOOD_EXPENSE"],[6,14,"FOOD_ITEM"]]}],
      ["Rs 30 Coffee\r",{"entities":[[3,5,"FOOD_EXPENSE"],[6,12,"FOOD_ITEM"]]}],
      
      ["Took a Rs 110 bus ride today.\r",{"entities":[[10,13,"TRAVEL_EXPENSE"],[14,17,"TRAVEL_MODE"]]}],
      ["Just spent Rs 10 on the metro.\r",{"entities":[[14,16,"TRAVEL_EXPENSE"],[24,29,"TRAVEL_MODE"]]}],
      ["Hopped into a taxi the ride cost me Rs 300.\r",{"entities":[[14,18,"TRAVEL_MODE"],[39,42,"TRAVEL_EXPENSE"]]}],
      ["Used the bus again; this time, it was Rs 200.\r",{"entities":[[9,12,"TRAVEL_MODE"],[41,44,"TRAVEL_EXPENSE"]]}],
      ["Spent Rs 100 for the metro.\r",{"entities":[[9,12,"TRAVEL_EXPENSE"],[21,26,"TRAVEL_MODE"]]}],
      ["Combining bus and metro set me back Rs 150 for travel.\r",{"entities":[[10,13,"TRAVEL_MODE"],[18,23,"TRAVEL_MODE"],[39,42,"TRAVEL_EXPENSE"]]}],
      ["Had a trip to Goa - expenses totaled Rs 5000.\r",{"entities":[[14,17,"TRAVEL_DESTINATION"],[40,44,"TRAVEL_EXPENSE"]]}],
      ["Opted for a Plane to London - the cost was Rs 25000.\r",{"entities":[[12,17,"TRAVEL_MODE"],[21,27,"TRAVEL_DESTINATION"],[45,51,"TRAVEL_EXPENSE"]]}],
      ["Traveled by train to Paris - spent Rs 4800.\r",{"entities":[[12,17,"TRAVEL_MODE"],[21,26,"TRAVEL_DESTINATION"],[38,42,"TRAVEL_EXPENSE"]]}],
      ["Quick auto-rickshaw ride in the city - just Rs 50.\r",{"entities":[[6,19,"TRAVEL_MODE"],[47,49,"TRAVEL_EXPENSE"]]}],
      ["Took the scooter for a short ride - expenses were Rs 20.\r",{"entities":[[9,16,"TRAVEL_MODE"],[53,55,"TRAVEL_EXPENSE"]]}],
      ["Weekend getaway to the Hill Station - spent Rs 800 on travel.\r",{"entities":[[23,35,"TRAVEL_DESTINATION"],[47,50,"TRAVEL_EXPENSE"]]}],
      ["Went on a cruise vacation to Maldives - expenses reached Rs 15000.\r",{"entities":[[10,16,"TRAVEL_MODE"],[29,37,"TRAVEL_DESTINATION"],[60,65,"TRAVEL_EXPENSE"]]}],
      ["Took a bicycle ride around the city - cost me only Rs 5.\r",{"entities":[[7,14,"TRAVEL_MODE"],[54,55,"TRAVEL_EXPENSE"]]}],
      ["Post-shopping rickshaw ride - spent Rs 30.\r",{"entities":[[14,22,"TRAVEL_MODE"],[39,41,"TRAVEL_EXPENSE"]]}],
      ["Enjoyed a road trip to the Mountains - expenses were Rs 2500 for fuel and tolls.\r",{"entities":[[27,36,"TRAVEL_DESTINATION"],[56,60,"TRAVEL_EXPENSE"]]}],
      ["Rented an electric scooter for the day - cost Rs 100.\r",{"entities":[[10,26,"TRAVEL_MODE"],[49,52,"TRAVEL_EXPENSE"]]}],
      ["Rs 110 bus\r",{"entities":[[3,6,"TRAVEL_EXPENSE"],[7,10,"TRAVEL_MODE"]]}],
      ["Rs 10 metro\r",{"entities":[[3,5,"TRAVEL_EXPENSE"],[6,11,"TRAVEL_MODE"]]}],
      ["Rs 300 taxi\r",{"entities":[[3,6,"TRAVEL_EXPENSE"],[7,11,"TRAVEL_MODE"]]}],
      ["Rs 200 bus\r",{"entities":[[3,6,"TRAVEL_EXPENSE"],[7,10,"TRAVEL_MODE"]]}],
      ["Rs 100 metro\r",{"entities":[[3,6,"TRAVEL_EXPENSE"],[7,12,"TRAVEL_MODE"]]}],
      ["Rs 150 bus and metro\r",{"entities":[[3,6,"TRAVEL_EXPENSE"],[7,10,"TRAVEL_MODE"],[15,20,"TRAVEL_MODE"]]}],
      ["Rs 5000 Goa trip\r",{"entities":[[3,7,"TRAVEL_EXPENSE"],[8,11,"TRAVEL_DESTINATION"]]}],
      ["Rs 25000 Plane to London\r",{"entities":[[3,8,"TRAVEL_EXPENSE"],[9,14,"TRAVEL_MODE"],[18,24,"TRAVEL_DESTINATION"]]}],
      ["Rs 4800 train to Paris\r",{"entities":[[3,7,"TRAVEL_EXPENSE"],[8,13,"TRAVEL_MODE"],[17,22,"TRAVEL_DESTINATION"]]}],
      ["Rs 50 auto-rickshaw\r",{"entities":[[3,5,"TRAVEL_EXPENSE"],[6,19,"TRAVEL_DESTINATION"]]}],
      ["Rs 20 scooter\r",{"entities":[[3,5,"TRAVEL_EXPENSE"],[6,13,"TRAVEL_MODE"]]}],
      ["Rs 800 Hill Station getaway\r",{"entities":[[3,6,"TRAVEL_EXPENSE"],[7,19,"TRAVEL_DESTINATION"]]}],
      ["Rs 15000 cruise to Maldives\r",{"entities":[[3,8,"TRAVEL_EXPENSE"],[9,15,"TRAVEL_MODE"],[19,27,"TRAVEL_DESTINATION"]]}],
      ["Rs 5 bicycle\r",{"entities":[[3,4,"TRAVEL_DESTINATION"],[5,12,"TRAVEL_MODE"]]}],["Rs 30 rickshaw\r",{"entities":[[3,5,"TRAVEL_EXPENSE"],[6,14,"TRAVEL_MODE"]]}],
      ["Rs 2500 road trip to Mountains\r",{"entities":[[3,7,"TRAVEL_EXPENSE"],[21,30,"TRAVEL_DESTINATION"]]}],
      ["Rs 100 electric scooter rental",{"entities":[[3,6,"TRAVEL_EXPENSE"],[7,23,"TRAVEL_MODE"]]}],

      ["I bought a Rs 700 shirt yesterday.\r",{"entities":[[14,17,"CLOTHING_EXPENSE"],[18,23,"CLOTHING_TYPE"]]}],
      ["Just purchased a Rs 450 pair of jeans.\r",{"entities":[[20,23,"CLOTHING_EXPENSE"],[32,37,"CLOTHING_TYPE"]]}],
      ["Bought a Rs 800 dress for the upcoming event.\r",{"entities":[[12,15,"CLOTHING_EXPENSE"],[16,21,"CLOTHING_TYPE"]]}],
      ["Got myself a Rs 300 hoodie to stay warm this winter.\r",{"entities":[[16,19,"CLOTHING_EXPENSE"],[20,26,"CLOTHING_TYPE"]]}],
      ["Spent Rs 2500 on a set of formal suits.\r",{"entities":[[9,13,"CLOTHING_EXPENSE"],[26,38,"CLOTHING_TYPE"]]}],
      ["Purchased a Rs 150 tie to match with my new shirt.\r",{"entities":[[15,18,"CLOTHING_EXPENSE"],[19,22,"CLOTHING_TYPE"]]}],
      ["Just got a Rs 350 skirt for the summer season.\r",{"entities":[[14,17,"CLOTHING_EXPENSE"],[18,23,"CLOTHING_TYPE"]]}],
      ["Bought a Rs 600 jacket for outdoor activities.\r",{"entities":[[12,15,"CLOTHING_EXPENSE"],[16,22,"CLOTHING_TYPE"]]}],
      ["Splurged on a Rs 2000 saree for the family function.\r",{"entities":[[17,21,"CLOTHING_EXPENSE"],[22,27,"CLOTHING_TYPE"]]}],
      ["Just picked up a Rs 100 pair of socks.\r",{"entities":[[20,23,"CLOTHING_EXPENSE"],[32,37,"CLOTHING_TYPE"]]}],
      ["Invested in a Rs 1200 leather jacket for the winter.\r",{"entities":[[17,21,"CLOTHING_EXPENSE"],[22,36,"CLOTHING_TYPE"]]}],
      ["Bought some Rs 50 underwear from the local store.\r",{"entities":[[15,17,"CLOTHING_EXPENSE"],[18,27,"CLOTHING_TYPE"]]}],
      ["Just grabbed a Rs 700 pair of sneakers for jogging.\r",{"entities":[[18,21,"CLOTHING_EXPENSE"],[30,38,"CLOTHING_TYPE"]]}],
      ["Spent Rs 900 on a pair of boots for the hiking trip.\r",{"entities":[[9,12,"CLOTHING_EXPENSE"],[26,31,"CLOTHING_TYPE"]]}],
      ["Got a Rs 180 t-shirt for casual wear.\r",{"entities":[[9,12,"CLOTHING_EXPENSE"],[13,20,"CLOTHING_TYPE"]]}],
      ["Just got a Rs 400 kurta for the festive season.\r",{"entities":[[14,17,"CLOTHING_EXPENSE"],[18,23,"CLOTHING_TYPE"]]}],
      ["Just snagged a Rs 550 sweatshirt for those chilly evenings.\r",{"entities":[[18,21,"CLOTHING_EXPENSE"],[22,32,"CLOTHING_TYPE"]]}],
      ["Bought a few clothes for Rs 5600.\r",{"entities":[[13,20,"CLOTHING_TYPE"],[28,32,"CLOTHING_EXPENSE"]]}],
      ["Picked up an Rs 850 oversized hoodie for ultimate comfort.\r",{"entities":[[16,19,"CLOTHING_EXPENSE"],[20,36,"CLOTHING_TYPE"]]}],
      ["Scored a killer deal on a Rs 1200 coat for the winter season.\r",{"entities":[[29,33,"CLOTHING_EXPENSE"],[34,38,"CLOTHING_TYPE"]]}],
      ["Splurged on a Rs 2000 suit for the upcoming wedding.\r",{"entities":[[17,21,"CLOTHING_EXPENSE"],[22,26,"CLOTHING_TYPE"]]}],
      ["Just invested in a Rs 1800 coatsuit for a stylish ensemble.\r",{"entities":[[22,26,"CLOTHING_EXPENSE"],[27,35,"CLOTHING_TYPE"]]}],
      ["Snagged a Rs 400 pair of cargo pants for a rugged look.\r",{"entities":[[13,16,"CLOTHING_EXPENSE"],[25,36,"CLOTHING_TYPE"]]}],
      ["Added a Rs 650 leather coat to my collection.\r",{"entities":[[11,14,"CLOTHING_EXPENSE"],[15,27,"CLOTHING_TYPE"]]}],
      ["Couldn't resist buying a Rs 300 denim jacket for the cool vibes.\r",{"entities":[[28,31,"CLOTHING_EXPENSE"],[32,44,"CLOTHING_TYPE"]]}],
      ["Spent Rs 700 on a sleek blazer for formal occasions.\r",{"entities":[[9,12,"CLOTHING_EXPENSE"],[24,30,"CLOTHING_TYPE"]]}],
      ["Spent Rs 10000 on clothing.\r",{"entities":[[9,14,"CLOTHING_EXPENSE"],[18,26,"CLOTHING_TYPE"]]}],
      ["Just grabbed a Rs 250 pair of shorts for the summer heat.\r",{"entities":[[18,21,"CLOTHING_EXPENSE"],[30,36,"CLOTHING_TYPE"]]}],
      ["Got myself a Rs 900 woolen sweater for the mountain getaway.\r",{"entities":[[16,19,"CLOTHING_EXPENSE"],[20,34,"CLOTHING_TYPE"]]}],
      ["Invested in a Rs 1500 cashmere scarf to stay cozy.\r",{"entities":[[17,21,"CLOTHING_EXPENSE"],[22,36,"CLOTHING_TYPE"]]}],
      ["Added a Rs 350 beanie to my winter accessories.\r",{"entities":[[11,14,"CLOTHING_EXPENSE"],[15,21,"CLOTHING_TYPE"]]}],
      ["Just got a Rs 200 pair of sandals for casual outings.\r",{"entities":[[14,17,"CLOTHING_EXPENSE"],[26,33,"CLOTHING_TYPE"]]}],
      ["Picked up a Rs 600 flannel shirt for a rustic look.\r",{"entities":[[15,18,"CLOTHING_EXPENSE"],[19,32,"CLOTHING_TYPE"]]}],
      ["Just snagged a Rs 550 kurta-pajama for the festive occasion.\r",{"entities":[[18,21,"CLOTHING_EXPENSE"],[22,34,"CLOTHING_TYPE"]]}],
      ["Scored a killer deal on a Rs 1200 sari for the family gathering.\r",{"entities":[[29,33,"CLOTHING_EXPENSE"],[34,38,"CLOTHING_TYPE"]]}],
      ["Picked up a Rs 850 lungi for those hot summer days.\r",{"entities":[[15,18,"CLOTHING_EXPENSE"],[19,24,"CLOTHING_TYPE"]]}],
      ["Splurged on a Rs 2000 sherwani for the wedding ceremony.\r",{"entities":[[17,21,"CLOTHING_EXPENSE"],[22,31,"CLOTHING_TYPE"]]}],
      ["Just invested in a Rs 1800 dhoti for traditional wear.\r",{"entities":[[22,26,"CLOTHING_EXPENSE"],[27,32,"CLOTHING_TYPE"]]}],
      ["Snagged a Rs 400 pair of flip-flops for the beach vacation.\r",{"entities":[[13,16,"CLOTHING_EXPENSE"],[25,35,"CLOTHING_TYPE"]]}],
      ["Added a Rs 650 cotton saree to my collection.\r",{"entities":[[11,14,"CLOTHING_EXPENSE"],[15,27,"CLOTHING_TYPE"]]}],
      ["Couldn't resist buying a Rs 300 khadi kurta for casual outings.\r",{"entities":[[28,31,"CLOTHING_EXPENSE"],[32,43,"CLOTHING_TYPE"]]}],
      ["Just grabbed a Rs 250 pair of chappals for everyday wear.\r",{"entities":[[18,21,"CLOTHING_EXPENSE"],[30,38,"CLOTHING_TYPE"]]}],
      ["Got myself a Rs 900 salwar kameez for special occasions.\r",{"entities":[[16,19,"CLOTHING_EXPENSE"],[20,33,"CLOTHING_TYPE"]]}],
      ["Invested in a Rs 1500 pashmina shawl to stay cozy.\r",{"entities":[[17,21,"CLOTHING_EXPENSE"],[22,36,"CLOTHING_TYPE"]]}],
      ["Invested in a Rs 50 vest for luxurious comfort.\r",{"entities":[[17,19,"CLOTHING_EXPENSE"],[20,24,"CLOTHING_TYPE"]]}],
      ["Added a Rs 350 bandhani dupatta to my ethnic collection.\r",{"entities":[[11,14,"CLOTHING_EXPENSE"],[15,31,"CLOTHING_TYPE"]]}],
      ["Just got a Rs 200 pair of mojris for the traditional touch.\r",{"entities":[[14,17,"CLOTHING_EXPENSE"],[26,32,"CLOTHING_TYPE"]]}],
      ["Picked up a Rs 600 pant saree for modern elegance.\r",{"entities":[[15,18,"CLOTHING_EXPENSE"],[19,29,"CLOTHING_TYPE"]]}],
      ["Just grabbed a Rs 150 pack of boxers for lounging around.\r",{"entities":[[18,21,"CLOTHING_EXPENSE"],[30,36,"CLOTHING_TYPE"]]}],
      ["Got myself a Rs 200 pair of panties for everyday comfort.\r",{"entities":[[16,19,"CLOTHING_EXPENSE"],[28,35,"CLOTHING_TYPE"]]}],
      ["Invested in some Rs 500 undies for comfort.\r",{"entities":[[20,23,"CLOTHING_EXPENSE"],[24,30,"CLOTHING_TYPE"]]}],
      ["Invested in some Rs 300 lingerie for special occasions.\r",{"entities":[[20,23,"CLOTHING_EXPENSE"],[24,32,"CLOTHING_TYPE"]]}],
      ["Picked up a Rs 250 set of briefs for gym sessions.\r",{"entities":[[15,18,"CLOTHING_EXPENSE"],[26,32,"CLOTHING_TYPE"]]}],
      ["Added a Rs 180 bralette to my collection.\r",{"entities":[[11,14,"CLOTHING_EXPENSE"],[15,23,"CLOTHING_TYPE"]]}],
      ["Just got a Rs 350 set of thermal underwear for winter outings.\r",{"entities":[[14,17,"CLOTHING_EXPENSE"],[25,42,"CLOTHING_TYPE"]]}],
      ["Picked up some Rs 120 cotton briefs for everyday wear.\r",{"entities":[[18,21,"CLOTHING_EXPENSE"],[22,35,"CLOTHING_TYPE"]]}],
      ["Got a Rs 180 set of lace panties for added flair.\r",{"entities":[[9,12,"CLOTHING_EXPENSE"],[20,32,"CLOTHING_TYPE"]]}],
      ["Invested in a Rs 200 pair of silk boxers for luxurious comfort.\r",{"entities":[[17,20,"CLOTHING_EXPENSE"],[29,40,"CLOTHING_TYPE"]]}],
      ["Just got a Rs 150 pair of seamless underwear for no-show confidence.\r",{"entities":[[14,17,"CLOTHING_EXPENSE"],[26,44,"CLOTHING_TYPE"]]}],
      ["Rs 700 shirt\r",{"entities":[[3,6,"CLOTHING_EXPENSE"],[7,12,"CLOTHING_TYPE"]]}],
      ["Rs 450 pair of jeans\r",{"entities":[[3,6,"CLOTHING_EXPENSE"],[15,20,"CLOTHING_TYPE"]]}],
      ["Rs 800 dress\r",{"entities":[[3,6,"CLOTHING_EXPENSE"],[7,12,"CLOTHING_TYPE"]]}],
      ["Rs 300 hoodie\r",{"entities":[[3,6,"CLOTHING_EXPENSE"],[7,13,"CLOTHING_TYPE"]]}],
      ["Rs 2500 formal suits\r",{"entities":[[3,7,"CLOTHING_EXPENSE"],[8,20,"CLOTHING_TYPE"]]}],
      ["Rs 150 tie\r",{"entities":[[3,6,"CLOTHING_EXPENSE"],[7,10,"CLOTHING_TYPE"]]}],
      ["Rs 350 skirt\r",{"entities":[[3,6,"CLOTHING_EXPENSE"],[7,12,"CLOTHING_TYPE"]]}],
      ["Rs 600 jacket\r",{"entities":[[3,6,"CLOTHING_EXPENSE"],[7,13,"CLOTHING_TYPE"]]}],
      ["Rs 2000 saree\r",{"entities":[[3,7,"CLOTHING_EXPENSE"],[8,13,"CLOTHING_TYPE"]]}],
      ["Rs 100 pair of socks\r",{"entities":[[3,6,"CLOTHING_EXPENSE"],[15,20,"CLOTHING_TYPE"]]}],
      ["Rs 1200 leather jacket\r",{"entities":[[3,7,"CLOTHING_EXPENSE"],[8,22,"CLOTHING_TYPE"]]}],
      ["Rs 50 underwear\r",{"entities":[[3,5,"CLOTHING_EXPENSE"],[6,15,"CLOTHING_TYPE"]]}],
      ["Rs 700 pair of sneakers\r",{"entities":[[3,6,"CLOTHING_EXPENSE"],[15,23,"CLOTHING_TYPE"]]}],
      ["Rs 900 pair of boots\r",{"entities":[[3,6,"CLOTHING_EXPENSE"],[15,20,"CLOTHING_TYPE"]]}],
      ["Rs 180 t-shirt\r",{"entities":[[3,6,"CLOTHING_EXPENSE"],[7,14,"CLOTHING_TYPE"]]}],
      ["Rs 400 kurta\r",{"entities":[[3,6,"CLOTHING_EXPENSE"],[7,12,"CLOTHING_TYPE"]]}],
      ["Rs 550 sweatshirt\r",{"entities":[[3,6,"CLOTHING_EXPENSE"],[7,17,"CLOTHING_TYPE"]]}],
      ["Rs 5600 clothes\r",{"entities":[[3,7,"CLOTHING_EXPENSE"],[8,15,"CLOTHING_TYPE"]]}],
      ["Rs 850 oversized hoodie\r",{"entities":[[3,6,"CLOTHING_EXPENSE"],[7,23,"CLOTHING_TYPE"]]}],
      ["Rs 1200 coat\r",{"entities":[[3,7,"CLOTHING_EXPENSE"],[8,12,"CLOTHING_TYPE"]]}],
      ["Rs 2000 suit\r",{"entities":[[3,7,"CLOTHING_EXPENSE"],[8,12,"CLOTHING_TYPE"]]}],
      ["Rs 1800 coatsuit\r",{"entities":[[3,7,"CLOTHING_EXPENSE"],[8,16,"CLOTHING_TYPE"]]}],
      ["Rs 400 pair of cargo pants\r",{"entities":[[3,6,"CLOTHING_EXPENSE"],[15,26,"CLOTHING_TYPE"]]}],
      ["Rs 650 leather coat\r",{"entities":[[3,6,"CLOTHING_EXPENSE"],[7,19,"CLOTHING_TYPE"]]}],
      ["Rs 300 denim jacket\r",{"entities":[[3,6,"CLOTHING_EXPENSE"],[7,19,"CLOTHING_TYPE"]]}],
      ["Rs 700 blazer\r",{"entities":[[3,6,"CLOTHING_EXPENSE"],[7,13,"CLOTHING_TYPE"]]}],
      ["Rs 10000 clothing\r",{"entities":[[3,8,"CLOTHING_EXPENSE"],[9,17,"CLOTHING_TYPE"]]}],
      ["Rs 250 pair of shorts\r",{"entities":[[3,6,"CLOTHING_EXPENSE"],[15,21,"CLOTHING_TYPE"]]}],
      ["Rs 900 woolen sweater\r",{"entities":[[3,6,"CLOTHING_EXPENSE"],[7,21,"CLOTHING_TYPE"]]}],
      ["Rs 1500 cashmere scarf\r",{"entities":[[3,7,"CLOTHING_EXPENSE"],[8,22,"CLOTHING_TYPE"]]}],
      ["Rs 350 beanie\r",{"entities":[[3,6,"CLOTHING_EXPENSE"],[7,13,"CLOTHING_TYPE"]]}],
      ["Rs 200 pair of sandals\r",{"entities":[[3,6,"CLOTHING_EXPENSE"],[15,22,"CLOTHING_TYPE"]]}],
      ["Rs 600 flannel shirt\r",{"entities":[[3,6,"CLOTHING_EXPENSE"],[7,20,"CLOTHING_TYPE"]]}],
      ["Rs 550 kurta-pajama\r",{"entities":[[3,6,"CLOTHING_EXPENSE"],[7,19,"CLOTHING_TYPE"]]}],
      ["Rs 1200 sari\r",{"entities":[[3,7,"CLOTHING_EXPENSE"],[8,12,"CLOTHING_TYPE"]]}],
      ["Rs 850 lungi\r",{"entities":[[3,6,"CLOTHING_EXPENSE"],[7,12,"CLOTHING_TYPE"]]}],
      ["Rs 2000 sherwani\r",{"entities":[[3,7,"CLOTHING_EXPENSE"],[8,16,"CLOTHING_TYPE"]]}],
      ["Rs 1800 dhoti\r",{"entities":[[3,7,"CLOTHING_EXPENSE"],[8,13,"CLOTHING_TYPE"]]}],
      ["Rs 400 pair of flip-flops\r",{"entities":[[3,6,"CLOTHING_EXPENSE"],[15,25,"CLOTHING_TYPE"]]}],
      ["Rs 650 cotton saree\r",{"entities":[[3,6,"CLOTHING_EXPENSE"],[7,19,"CLOTHING_TYPE"]]}],
      ["Rs 300 khadi kurta\r",{"entities":[[3,6,"CLOTHING_EXPENSE"],[7,18,"CLOTHING_TYPE"]]}],
      ["Rs 250 pair of chappals\r",{"entities":[[3,6,"CLOTHING_EXPENSE"],[15,23,"CLOTHING_TYPE"]]}],
      ["Rs 900 salwar kameez\r",{"entities":[[3,6,"CLOTHING_EXPENSE"],[7,20,"CLOTHING_TYPE"]]}],
      ["Rs 1500 pashmina shawl\r",{"entities":[[3,7,"CLOTHING_EXPENSE"],[8,22,"CLOTHING_TYPE"]]}],
      ["Rs 50 vest\r",{"entities":[[3,5,"CLOTHING_EXPENSE"],[6,10,"CLOTHING_TYPE"]]}],
      ["Rs 350 bandhani dupatta\r",{"entities":[[3,6,"CLOTHING_EXPENSE"],[7,23,"CLOTHING_TYPE"]]}],
      ["Rs 200 pair of mojris\r",{"entities":[[3,6,"CLOTHING_EXPENSE"],[15,21,"CLOTHING_TYPE"]]}],
      ["Rs 600 pant saree\r",{"entities":[[3,6,"CLOTHING_EXPENSE"],[7,17,"CLOTHING_TYPE"]]}],
      ["Rs 150 pack of boxers\r",{"entities":[[3,6,"CLOTHING_EXPENSE"],[15,21,"CLOTHING_TYPE"]]}],
      ["Rs 200 pair of panties\r",{"entities":[[3,6,"CLOTHING_EXPENSE"],[15,22,"CLOTHING_TYPE"]]}],
      ["Rs 500 undies\r",{"entities":[[3,6,"CLOTHING_EXPENSE"],[7,13,"CLOTHING_TYPE"]]}],
      ["Rs 300 lingerie\r",{"entities":[[3,6,"CLOTHING_EXPENSE"],[7,15,"CLOTHING_TYPE"]]}],
      ["Rs 250 set of briefs\r",{"entities":[[3,6,"CLOTHING_EXPENSE"],[14,20,"CLOTHING_TYPE"]]}],
      ["Rs 180 bralette\r",{"entities":[[3,6,"CLOTHING_EXPENSE"],[7,15,"CLOTHING_TYPE"]]}],
      ["Rs 350 set of thermal underwear\r",{"entities":[[3,6,"CLOTHING_EXPENSE"],[14,31,"CLOTHING_TYPE"]]}],
      ["Rs 120 cotton briefs\r",{"entities":[[3,6,"CLOTHING_EXPENSE"],[7,20,"CLOTHING_TYPE"]]}],
      ["Rs 180 set of lace panties\r",{"entities":[[3,6,"CLOTHING_EXPENSE"],[14,26,"CLOTHING_TYPE"]]}],
      ["Rs 200 pair of silk boxers\r",{"entities":[[3,6,"CLOTHING_EXPENSE"],[15,26,"CLOTHING_TYPE"]]}],
      ["Rs 150 pair of seamless underwear\r",{"entities":[[3,6,"CLOTHING_EXPENSE"],[15,33,"CLOTHING_TYPE"]]}]


    ]  
  }